aws_clients_python_lib/__init__.py
aws_clients_python_lib/aws_lambda.py
aws_clients_python_lib/parameter_store.py
aws_clients_python_lib/py.typed
aws_clients_python_lib/secrets_manager.py
aws_clients_python_lib-0.10.0.0.dist-info/METADATA
aws_clients_python_lib-0.10.0.0.dist-info/WHEEL
aws_clients_python_lib-0.10.0.0.dist-info/licenses/LICENSE.md
aws_clients_python_lib-0.10.0.0.dist-info/licenses/LICENSE.pdf
aws_clients_python_lib-0.10.0.0.dist-info/RECORD
