Metadata-Version: 2.4
Name: aws-clients-python-lib
Version: 0.10.0.0
Summary: AWS Clients Python Library
Author-email: "Jeffrey Jonathan Jennings (J3)" <j3@thej3.com>
License-File: LICENSE.md
License-File: LICENSE.pdf
Requires-Python: >=3.11.9
Requires-Dist: boto3>=1.40.30
Requires-Dist: pytest>=8.4.2
